{"type":"Topology","transform":{"scale":[0.0015625187593796895,0.0016346963481740874],"translate":[74.472183,27.658255]},"objects":{"S07_PC":{"type":"GeometryCollection","geometries":[{"type":"Polygon","arcs":[[0,1]],"properties":{"ST_CODE":"S07","ST_NAME":"HARYANA","PC_NAME":"Faridabad","PC_TYPE":"GEN","AREA":3549.17357198,"PC_NO":6}},{"type":"Polygon","arcs":[[2,3,4,5,6,7]],"properties":{"ST_CODE":"S07","ST_NAME":"HARYANA","PC_NAME":"Bhiwani","PC_TYPE":"GEN","AREA":6287.74727405,"PC_NO":8}},{"type":"Polygon","arcs":[[8,9,10,-6]],"properties":{"ST_CODE":"S07","ST_NAME":"HARYANA","PC_NAME":"Rohtak","PC_TYPE":"GEN","AREA":3518.96447301,"PC_NO":5}},{"type":"Polygon","arcs":[[11,-3,12]],"properties":{"ST_CODE":"S07","ST_NAME":"HARYANA","PC_NAME":"Sirsa","PC_TYPE":"SC","AREA":7278.66523138,"PC_NO":10}},{"type":"Polygon","arcs":[[13,14,15,-4,-12,16]],"properties":{"ST_CODE":"S07","ST_NAME":"HARYANA","PC_NAME":"Hissar","PC_TYPE":"GEN","AREA":4413.69611541,"PC_NO":9}},{"type":"Polygon","arcs":[[17,18,19,-15]],"properties":{"ST_CODE":"S07","ST_NAME":"HARYANA","PC_NAME":"Karnal","PC_TYPE":"GEN","AREA":3544.59123959,"PC_NO":3}},{"type":"Polygon","arcs":[[20,21]],"properties":{"ST_CODE":"S07","ST_NAME":"HARYANA","PC_NAME":"Ambala","PC_TYPE":"SC","AREA":3819.14047979,"PC_NO":1}},{"type":"Polygon","arcs":[[-21,22,-18,-14,23]],"properties":{"ST_CODE":"S07","ST_NAME":"HARYANA","PC_NAME":"Kurukshetra","PC_TYPE":"GEN","AREA":3729.68903568,"PC_NO":2}},{"type":"Polygon","arcs":[[-9,-5,-16,-20,24]],"properties":{"ST_CODE":"S07","ST_NAME":"HARYANA","PC_NAME":"Sonepat","PC_TYPE":"GEN","AREA":3353.49690532,"PC_NO":4}},{"type":"Polygon","arcs":[[-7,-11,25,-1,26]],"properties":{"ST_CODE":"S07","ST_NAME":"HARYANA","PC_NAME":"Mahendragarh","PC_TYPE":"GEN","AREA":4356.41609779,"PC_NO":7}}]}},"arcs":[[[1524,347],[51,54],[49,1],[32,-74],[38,-24],[50,16],[-3,20],[32,38],[-34,10],[-18,21],[0,31],[17,17]],[[1738,457],[40,9],[-10,30],[70,24],[15,-24],[49,-3],[-14,-14],[36,-12],[25,-24],[0,-20],[-27,-14],[19,-13],[-26,-18],[53,-40],[-24,-4],[-5,-20],[27,-6],[-45,-47],[45,-85],[-42,-13],[-2,-28],[-32,4],[-12,-14],[-42,-11],[-15,-19],[-46,-20],[-49,17],[-17,-18],[-53,17],[-15,-17],[36,-21],[-34,-7],[-36,-22],[-3,-21],[-41,-3],[-8,33],[13,61],[22,14],[-8,19],[1,58],[-10,34],[24,67],[-51,29],[9,12],[-31,20]],[[591,953],[22,21],[-9,46],[36,8],[27,-35],[19,3],[-5,-28],[35,-1],[46,-27]],[[762,940],[-7,-52],[93,-22],[26,-14],[-11,-17],[53,-18],[12,11],[32,-19],[0,50],[-15,30],[5,47],[12,7],[35,-31],[88,-30],[68,7],[22,16]],[[1175,905],[-2,-33]],[[1173,872],[-42,-24],[0,-27],[-18,-33],[18,-28],[32,-9],[0,-49],[26,2],[52,-37],[-15,-32],[12,-23],[29,-3],[13,-31],[-20,-7],[-7,-28],[-15,21],[-39,10],[-9,-63],[-32,-7],[5,-31]],[[1163,473],[-34,18],[-59,-24],[-15,-39],[-44,-6],[-4,-37],[-16,-11]],[[991,374],[-82,69],[-78,14],[5,26],[-30,7],[-24,38],[-25,12],[-14,37],[-34,10],[-15,28],[-22,72],[10,22],[-24,18],[-8,43],[22,4],[0,41],[-47,10],[-4,24],[-30,6],[1,41],[-13,0],[22,48],[-10,9]],[[1173,872],[89,-20],[61,23],[8,-21],[54,-16],[14,13],[37,-13],[20,-44],[39,-27],[39,-54],[-34,-17],[-23,-31],[3,-23],[63,-51]],[[1543,591],[-24,-47],[24,-17]],[[1543,527],[-56,-34],[-34,14],[-27,-7],[5,-37],[17,-24],[-12,-11],[-30,14],[-29,31],[-27,-54],[-46,7],[-7,13],[-25,-20],[-26,9],[0,-22],[-25,10],[10,23],[-17,13],[-27,-22],[-27,20],[3,23]],[[948,1261],[-13,-10],[18,-84],[-44,-24],[-18,6],[-19,-26],[-44,-3],[12,-54],[-10,-52],[-55,-40],[-13,-34]],[[591,953],[-9,17],[-35,-14],[1,35],[-59,-37],[-32,17],[-49,-20],[-21,5],[-22,34],[-27,-9],[-28,12],[-12,42],[-46,26],[-27,-2],[-22,-18],[-83,1],[-12,-24],[-22,14],[-41,64],[31,2],[20,37],[-22,25],[-2,60],[21,48],[-16,17],[-37,-23],[-40,16],[3,31],[46,20],[13,21],[-30,20],[3,23],[85,-21],[30,41],[44,-4],[27,11],[29,-17],[41,-7],[47,-51],[43,1],[17,30],[13,-13],[-8,-52],[35,-22],[29,34],[24,-58],[-22,0],[-24,-44],[36,-38],[18,-33],[41,9],[-10,28],[22,37],[35,21],[43,64],[112,-38],[18,15],[31,-11],[3,27],[51,12],[32,-5],[19,-27],[52,-21]],[[1119,1332],[27,-29],[-8,-23],[61,-3],[27,-17],[10,-49],[-34,-37],[58,-2],[17,22],[44,-7]],[[1321,1187],[-12,-44],[25,-10],[9,-37]],[[1343,1096],[-34,-25],[-25,1],[5,-71],[-9,-11],[-34,10],[-54,0],[-27,-13],[-49,3],[-7,-12],[22,-35],[36,-9],[8,-29]],[[948,1261],[59,10],[36,37],[37,3],[39,21]],[[1321,1187],[61,20],[5,14],[37,14],[-27,9],[19,14],[-7,23],[7,72],[47,-4],[73,7],[81,54],[41,-11],[34,25],[51,-38]],[[1743,1386],[-17,-20],[3,-65],[-25,-43],[-19,-7],[-15,-48],[12,-33],[-29,-14],[15,-34],[-8,-43],[25,-8],[15,-26],[-5,-23],[16,-21],[-19,-13],[13,-31],[-13,-31],[10,-12]],[[1702,914],[-64,6],[-12,23],[-65,-3],[-17,-10],[-42,13],[-15,41],[-31,-13],[-64,16],[2,51],[54,10],[15,54],[-88,17],[-32,-23]],[[1799,1445],[-60,20],[-1,42],[-51,32],[-24,-4],[-7,-23],[-39,17],[-27,0],[-18,23],[-24,0],[-9,23],[-37,8],[-20,-44],[-27,6],[-70,-23]],[[1385,1522],[5,28],[-28,28],[-34,-15],[13,24],[32,2],[41,34],[44,24],[-25,24],[30,19],[48,1],[35,-10],[17,60],[-24,20],[19,4],[0,34],[-37,47],[-15,53],[5,32],[-19,10],[-25,40],[27,18],[10,-21],[52,1],[29,-55],[31,-6],[-4,-21],[75,-24],[34,-30],[5,-50],[-22,-35],[51,-21],[0,-12],[54,-27],[18,6],[56,-30],[39,-3],[29,20],[12,-22],[32,-12],[-7,-48],[-44,-50],[-71,-58],[-7,-16],[-67,-40]],[[1799,1445],[-56,-59]],[[1119,1332],[9,21],[-31,7],[-8,31],[56,96],[-34,11],[7,20],[69,-33],[5,25],[39,-13],[12,44],[30,-50],[39,-16],[65,35],[8,12]],[[1702,914],[0,-38],[31,-51],[-7,-31],[27,-30],[-34,-45],[-12,15],[-51,6],[-12,-23],[-30,3],[-34,-24],[15,-61],[-25,-30],[12,-13],[-39,-1]],[[1543,527],[39,-11],[39,22],[74,-28],[5,-34],[38,-19]],[[1524,347],[-39,-19],[0,-27],[-64,-38],[-19,4],[5,-54],[-37,-6],[-32,-29],[-19,49],[-25,30],[-27,0],[22,33],[-31,8],[-34,-10],[-47,33],[22,-48],[-29,-9],[34,-12],[-25,-36],[-26,30],[-17,4],[-76,-41],[39,-20],[-5,-40],[30,-45],[-27,-23],[-45,37],[-77,-18],[-35,71],[18,-8],[17,25],[-3,21],[25,51],[-32,-7],[-32,10],[8,14],[65,33],[29,-13],[-21,41],[-29,19],[6,17]]]}